{
  "publicApplicationId": "com.ula.quickcalc",
  "description": "The QuickCalc is a tool which allows you to quickly perform some basic day to day functions.  It is made up of 6 different calculators which are useful while shopping, and also when some basic units of measure need to be converted to different standards.   1.  Price Compare – Calculates the best value of an item based on quantity, units, and price. 2.  Discount Calculator – Calculates the price of an item minus a discount plus the tax. 3.  Convert Temperature – Converts a given temperature from Fahrenheit to Celsius and vice versa. 4.  Convert Weight – Converts a given weight to different weight units such as gram, kilogram, ton, ounce, and pound. 5.  Convert Length & Distance – Converts a given length or distance to a different unit such as millimeters, centimeters, meters, kilometers, inches, feet, yard, mile, nautical mile. 6.  Convert Shoe Size – Converts a shoe size from a given size standard to a different standard such as US, UK, EU, and Japan. ",
  "version": "1.0.0",
  "versionNote": "",
  "homeURL": "http://www.fastovsky.com",
  "supportURL": "http://forums.precentral.net/showthread.php?p=2291743#post2291743",
  "custsupportemail": "ufastovsky@yahoo.com",
  "custsupportphonenum": "..",
  "copyright": "copyright 2010 Ursula Fastovsky",
  "licenseURL": "",
  "locale": "en_US",
  "appSize": 33586,
  "installSize": 2505754,
  "isEncrypted": false,
  "adultRating": false,
  "islocationbased": false,
  "lastModifiedTime": "2010-03-10T10:09:15-05:00",
  "mediaLink": null,
  "mediaIcon": null,
  "attributes": {
    "provides": {
      "noApp": false,
      "dockMode": false,
      "universalSearch": false,
      "connectors": [],
      "services": [],
      "optimizedUserExperience": false
    }
  },
  "price": 0.99,
  "currency": "USD",
  "isAdvertized": false,
  "filename": "com.ula.quickcalc_1.0.0_all.ipk",
  "free": false,
  "touchpad_exclusive": false,
  "images": {
    "1": {
      "thumbnail": "2058/en/images/1/S/Main.jpg",
      "screenshot": "2058/en/images/1/L/Main.jpg",
      "orientation": "P",
      "device": "P"
    },
    "2": {
      "thumbnail": "2058/en/images/2/S/price.jpg",
      "screenshot": "2058/en/images/2/L/price.jpg",
      "orientation": "P",
      "device": "P"
    },
    "3": {
      "thumbnail": "2058/en/images/3/S/discount.jpg",
      "screenshot": "2058/en/images/3/L/discount.jpg",
      "orientation": "P",
      "device": "P"
    },
    "4": {
      "thumbnail": "2058/en/images/4/S/temperature.jpg",
      "screenshot": "2058/en/images/4/L/temperature.jpg",
      "orientation": "P",
      "device": "P"
    },
    "5": {
      "thumbnail": "2058/en/images/5/S/shoe.jpg",
      "screenshot": "2058/en/images/5/L/shoe.jpg",
      "orientation": "P",
      "device": "P"
    }
  },
  "originalFileName": "com.ula.quickcalc_1.0.0_all.ipk",
  "starRating": 4
}
